drone_controller/__init__.py
drone_controller/main.py
drone_controller/calculation_layer/__init__.py
drone_controller/calculation_layer/thrust_calculator.py
drone_controller/exception/__init__.py
drone_controller/exception/exceptions.py
drone_controller/input_layer/__init__.py
drone_controller/input_layer/drone_physics.py
drone_controller/input_layer/drone_state.py
drone_controller/input_layer/drone_state_mapper.py
drone_controller/input_layer/request_handler.py
drone_controller/util/__init__.py
drone_controller/util/list_operators.py
test/__init__.py
test/test_main.py
test/drone_controller/__init__.py
test/drone_controller/calculation_layer/__init__.py
test/drone_controller/calculation_layer/test_thrust_calculator.py
test/drone_controller/input_layer/__init__.py
test/drone_controller/input_layer/test_drone_physics.py
test/drone_controller/input_layer/test_drone_state.py
test/drone_controller/input_layer/test_drone_state_mapper.py
test/drone_controller/input_layer/test_request_handler.py
test/drone_controller/util/__init__.py
test/drone_controller/util/test_list_operators.py
DroneController-1.1.0.dist-info/LICENSE
DroneController-1.1.0.dist-info/METADATA
DroneController-1.1.0.dist-info/WHEEL
DroneController-1.1.0.dist-info/top_level.txt
DroneController-1.1.0.dist-info/RECORD
