Metadata-Version: 2.1
Name: DroneController
Version: 1.1.0
Summary: A python module that calculates thrusts for various aircrafts from all sorts of inputs. 
Home-page: https://www.github.com/treeandsea/DroneController
Author: Segelzwerg, TreeKid
Author-email: marcel.haas@hhu.de
License: GPL-3.0
Download-URL: https://github.com/treeandsea/DroneController/releases
Keywords: drone flying controller aviation
Platform: UNKNOWN
Requires-Python: >=3.6
Requires-Dist: numpy
